pycrimeprediction/__init__.py
pycrimeprediction/add_if_crime.py
pycrimeprediction/perform_analysis.py
pycrimeprediction/read_save_data.py
pycrimeprediction/time_period.py
pycrimeprediction-0.1.0.dist-info/LICENSE
pycrimeprediction-0.1.0.dist-info/METADATA
pycrimeprediction-0.1.0.dist-info/WHEEL
pycrimeprediction-0.1.0.dist-info/RECORD
