Metadata-Version: 2.1
Name: pycrimeprediction
Version: 0.1.0
Summary: group 10 description
License: MIT
Author: Cassandra Zhang
Requires-Python: >=3.9,<4.0
Classifier: License :: OSI Approved :: MIT License
Classifier: Programming Language :: Python :: 3
Classifier: Programming Language :: Python :: 3.9
Classifier: Programming Language :: Python :: 3.10
Classifier: Programming Language :: Python :: 3.11
Classifier: Programming Language :: Python :: 3.12
Requires-Dist: pandas (>=2.2.1,<3.0.0)
Requires-Dist: scikit-learn (>=1.4.2,<2.0.0)
